pyMigrate/__init__.py
pyMigrate/deps_handler.py
pyMigrate/env.py
pyMigrate/parser_import.py
pyMigrate/walk.py
pymigrate_np-0.0.1.dist-info/METADATA
pymigrate_np-0.0.1.dist-info/RECORD
pymigrate_np-0.0.1.dist-info/WHEEL
pymigrate_np-0.0.1.dist-info/top_level.txt
