Metadata-Version: 2.1
Name: pymigrate-np
Version: 0.0.1
Summary: A tool for converting your normal python project to a virtual environment, with all the dependencies automatically set up
Home-page: https://github.com/Narasimha1997/pyMigrate
Author: Narasimha Prasanna HN
Author-email: narasimhaprasannahn@example.com
License: UNKNOWN
Platform: UNKNOWN
Classifier: Programming Language :: Python :: 3
Classifier: License :: OSI Approved :: MIT License
Classifier: Operating System :: OS Independent
